<?xml version="1.0" encoding="utf-8"?>
<GameData>
  <LocalizedText>
	<!-- WORLD RANKINGS SCREEN -->
	<Replace Tag="LOC_HSD_VICTORY_INTRO" Language="en_US">
      <Text>Achieve a [COLOR_Civ6Yellow]HISTORICAL VICTORY[ENDCOLOR] by completing all challenges for your civilization to unlock the [COLOR_Civ6Yellow]HISTORICAL VICTORY PROJECT[ENDCOLOR]. Victory progress can be tracked from the Civilization tabs below. Completing a challenge grants bonus Era Score.[NEWLINE][NEWLINE]</Text>
    </Replace>
	<Replace Tag="LOC_HSD_VICTORY_OVERALL_TOOLTIP" Language="en_US">
      <Text>[ICON_CAPITAL]Challenges Completed: {1_current}/{2_total}{3_totalVictorySummary}</Text>
    </Replace>
	<Replace Tag="LOC_HSD_VICTORY_COMPLETED_TOOLTIP" Language="en_US">
      <Text>[NEWLINE][ICON_BULLET]{1_VictoryName}: {2_year}</Text>
    </Replace>
	<Replace Tag="LOC_HSD_OBJECTIVE_STATUS" Language="en_US">
      <Text>[COLOR_Civ6Yellow] {1_current}/{2_total}[ENDCOLOR]</Text>
    </Replace>
	<!-- CIVILIZATION VICTORY TEXT -->
	
	<!-- GAUL -->
	<!-- Victory 1 -->
	<Replace Tag="LOC_HSD_VICTORY_CIVILIZATION_GAUL_1_NAME" Language="en_US">
	  <Text>Druidic Lore</Text>
	</Replace>
	<Replace Tag="LOC_HSD_VICTORY_CIVILIZATION_GAUL_1_DESC" Language="en_US">
	  <Text>Control the Stonehenge and Oracle wonders by 250BC</Text>
	</Replace>
	<Replace Tag="LOC_HSD_VICTORY_CIVILIZATION_GAUL_1_DETAILS_ROW_1" Language="en_US">
	  <Text>Control the Stonehenge wonder by 250BC</Text>
	</Replace>
	<Replace Tag="LOC_HSD_VICTORY_CIVILIZATION_GAUL_1_DETAILS_ROW_2" Language="en_US">
	  <Text>Control the Oracle wonder by 250BC</Text>
	</Replace>
	<!-- Victory 2 -->
	<Replace Tag="LOC_HSD_VICTORY_CIVILIZATION_GAUL_2_NAME" Language="en_US">
	  <Text>Celtic Migrations</Text>
	</Replace>
	<Replace Tag="LOC_HSD_VICTORY_CIVILIZATION_GAUL_2_DESC" Language="en_US">
	  <Text>Control 5 cities that border other players by 50BC</Text>
	</Replace>
	<Replace Tag="LOC_HSD_VICTORY_CIVILIZATION_GAUL_2_DETAILS_ROW_1" Language="en_US">
	  <Text>Control 5 cities that border other players by 50BC</Text>
	</Replace>
	<!-- Victory 3 -->
	<Replace Tag="LOC_HSD_VICTORY_CIVILIZATION_GAUL_3_NAME" Language="en_US">
	  <Text>Gallic Warriors</Text>
	</Replace>
	<Replace Tag="LOC_HSD_VICTORY_CIVILIZATION_GAUL_3_DESC" Language="en_US">
	  <Text>Kill 20 units with the Gaesatae unique unit</Text>
	</Replace>
	<Replace Tag="LOC_HSD_VICTORY_CIVILIZATION_GAUL_3_DETAILS_ROW_1" Language="en_US">
	  <Text>Kill 20 units with the Gaesatae unique unit</Text>
	</Replace>
	
	<!-- MAYA -->
	<!-- Victory 1 -->
	<Replace Tag="LOC_HSD_VICTORY_CIVILIZATION_MAYA_1_NAME" Language="en_US">
	  <Text>Chichen Itza</Text>
	</Replace>
	<Replace Tag="LOC_HSD_VICTORY_CIVILIZATION_MAYA_1_DESC" Language="en_US">
	  <Text>Build the Chichen Itza wonder</Text>
	</Replace>
	<Replace Tag="LOC_HSD_VICTORY_CIVILIZATION_MAYA_1_DETAILS_ROW_1" Language="en_US">
	  <Text>Build the Chichen Itza wonder</Text>
	</Replace>
	<!-- Victory 2 -->
	<Replace Tag="LOC_HSD_VICTORY_CIVILIZATION_MAYA_2_NAME" Language="en_US">
	  <Text>House of the K'uhul Ajaw</Text>
	</Replace>
	<Replace Tag="LOC_HSD_VICTORY_CIVILIZATION_MAYA_2_DESC" Language="en_US">
	  <Text>Control the city with the highest population in the world by the end of the Medieval Era</Text>
	</Replace>
	<Replace Tag="LOC_HSD_VICTORY_CIVILIZATION_MAYA_2_DETAILS_ROW_1" Language="en_US">
	  <Text>Control the city with the highest population in the world by the end of the Medieval Era</Text>
	</Replace>
	<!-- Victory 3 -->
	<Replace Tag="LOC_HSD_VICTORY_CIVILIZATION_MAYA_3_NAME" Language="en_US">
	  <Text>Long Count Calendar</Text>
	</Replace>
	<Replace Tag="LOC_HSD_VICTORY_CIVILIZATION_MAYA_3_DESC" Language="en_US">
	  <Text>Have more technologies than a European civilization by the end of the Industrial Era</Text>
	</Replace>
	<Replace Tag="LOC_HSD_VICTORY_CIVILIZATION_MAYA_3_DETAILS_ROW_1" Language="en_US">
	  <Text>Have more technologies than a European civilization by the end of the Industrial Era</Text>
	</Replace>
	
	<!-- NORWAY -->
	<!-- Victory 1 -->
	<Replace Tag="LOC_HSD_VICTORY_CIVILIZATION_NORWAY_1_NAME" Language="en_US">
	  <Text>The Viking Age</Text>
	</Replace>
	<Replace Tag="LOC_HSD_VICTORY_CIVILIZATION_NORWAY_1_DESC" Language="en_US">
	  <Text>Pillage 30 times with the Viking Longship unique unit</Text>
	</Replace>
	<Replace Tag="LOC_HSD_VICTORY_CIVILIZATION_NORWAY_1_DETAILS_ROW_1" Language="en_US">
	  <Text>Viking Longship pillage count</Text>
	</Replace>
	<Replace Tag="LOC_HSD_VICTORY_CIVILIZATION_NORWAY_1_FLOATER_1" Language="en_US">
	  <Text>Viking Longship pillage count: {1_pillageCount}</Text>
	</Replace>
	
	<!-- PERSIA -->
	<!-- Victory 1 -->
	<Replace Tag="LOC_HSD_VICTORY_CIVILIZATION_PERSIA_1_NAME" Language="en_US">
	  <Text>The Immortals</Text>
	</Replace>
	<Replace Tag="LOC_HSD_VICTORY_CIVILIZATION_PERSIA_1_DESC" Language="en_US">
	  <Text>Have at least 5 Immortal unique units and control at least 2 other capitals by 450 BC</Text>
	</Replace>
	<Replace Tag="LOC_HSD_VICTORY_CIVILIZATION_PERSIA_1_DETAILS_ROW_1" Language="en_US">
	  <Text>Have at least 5 Immortal unique units by 450 BC</Text>
	</Replace>
	<Replace Tag="LOC_HSD_VICTORY_CIVILIZATION_PERSIA_1_DETAILS_ROW_2" Language="en_US">
	  <Text>Control at least 2 other capitals by 450 BC</Text>
	</Replace>
	<!-- Victory 2 -->
	<Replace Tag="LOC_HSD_VICTORY_CIVILIZATION_PERSIA_2_NAME" Language="en_US">
	  <Text>Achaemenid Architecture</Text>
	</Replace>
	<Replace Tag="LOC_HSD_VICTORY_CIVILIZATION_PERSIA_2_DESC" Language="en_US">
	  <Text>Build the Apadana Wonder and at least 3 Pairidaeza (Persian unique improvement) by 350 BC</Text>
	</Replace>
	<Replace Tag="LOC_HSD_VICTORY_CIVILIZATION_PERSIA_2_DETAILS_ROW_1" Language="en_US">
	  <Text>Build the Apadana Wonder by 350 BC</Text>
	</Replace>
	<Replace Tag="LOC_HSD_VICTORY_CIVILIZATION_PERSIA_2_DETAILS_ROW_2" Language="en_US">
	  <Text>Build at least 3 Pairidaeza by 350 BC</Text>
	</Replace>
	<!-- Victory 3 -->
	<Replace Tag="LOC_HSD_VICTORY_CIVILIZATION_PERSIA_3_NAME" Language="en_US">
	  <Text>King of Kings</Text>
	</Replace>
	<Replace Tag="LOC_HSD_VICTORY_CIVILIZATION_PERSIA_3_DESC" Language="en_US">
	  <Text>Be the Suzerain of at least 5 city-states at the same time</Text>
	</Replace>
	<Replace Tag="LOC_HSD_VICTORY_CIVILIZATION_PERSIA_3_DETAILS_ROW_1" Language="en_US">
	  <Text>Suzerain of at least 5 city-states</Text>
	</Replace>
	
	<!-- ROME -->
	<!-- Victory 1 -->
	<Replace Tag="LOC_HSD_VICTORY_CIVILIZATION_ROME_1_NAME" Language="en_US">
      <Text>Pax Romana</Text>
    </Replace>
	<Replace Tag="LOC_HSD_VICTORY_CIVILIZATION_ROME_1_DESC" Language="en_US">
      <Text>Build the Colosseum, 4 Bath districts, and 15 road plots within your territory by 100AD</Text>
    </Replace>
	<Replace Tag="LOC_HSD_VICTORY_CIVILIZATION_ROME_1_DETAILS_ROW_1" Language="en_US">
      <Text>Build the Colosseum by 100AD</Text>
    </Replace>
	<Replace Tag="LOC_HSD_VICTORY_CIVILIZATION_ROME_1_DETAILS_ROW_2" Language="en_US">
      <Text>Build 4 Bath districts by 100AD</Text>
    </Replace>
	<Replace Tag="LOC_HSD_VICTORY_CIVILIZATION_ROME_1_DETAILS_ROW_3" Language="en_US">
      <Text>Build 15 roads in your territory by 100AD</Text>
    </Replace>
	<!-- Victory 2 -->
	<Replace Tag="LOC_HSD_VICTORY_CIVILIZATION_ROME_2_NAME" Language="en_US">
      <Text>Imperium Romanum</Text>
    </Replace>
	<Replace Tag="LOC_HSD_VICTORY_CIVILIZATION_ROME_2_DESC" Language="en_US">
      <Text>Control 20% of land plots in Europe and 5 cities on other continents by 200AD</Text>
    </Replace>
	<Replace Tag="LOC_HSD_VICTORY_CIVILIZATION_ROME_2_DETAILS_ROW_1" Language="en_US">
      <Text>Control 20% of land plots in Europe by 200AD</Text>
    </Replace>
	<Replace Tag="LOC_HSD_VICTORY_CIVILIZATION_ROME_2_DETAILS_ROW_2" Language="en_US">
      <Text>Control 5 cities outside of Europe by 200AD</Text>
    </Replace>
	<!-- Victory 3 -->
	<Replace Tag="LOC_HSD_VICTORY_CIVILIZATION_ROME_3_NAME" Language="en_US">
      <Text>Mare Nostrum</Text>
    </Replace>
	<Replace Tag="LOC_HSD_VICTORY_CIVILIZATION_ROME_3_DESC" Language="en_US">
      <Text>Control all plots of a sea territory</Text>
    </Replace>
	<Replace Tag="LOC_HSD_VICTORY_CIVILIZATION_ROME_3_DETAILS_ROW_1" Language="en_US">
      <Text>Control all plots of a sea territory</Text>
    </Replace>
	<!-- JULIUS CAESAR -->
	<Replace Tag="LOC_HSD_VICTORY_LEADER_JULIUS_CAESAR_1_NAME" Language="en_US">
      <Text>Veni, Vidi, Vici</Text>
    </Replace>
	<Replace Tag="LOC_HSD_VICTORY_LEADER_JULIUS_CAESAR_1_DESC" Language="en_US">
      <Text>Control all capitals in the southern half of Europe at the end of the Classical Era</Text>
    </Replace>
	<Replace Tag="LOC_HSD_VICTORY_LEADER_JULIUS_CAESAR_1_DETAILS_ROW_1" Language="en_US">
      <Text>Control all capitals in the southern half of Europe at the end of the Classical Era : </Text>
    </Replace>
  </LocalizedText>
</GameData>
